esi_utils_transfer/__init__.py
esi_utils_transfer/copysender.py
esi_utils_transfer/emailsender.py
esi_utils_transfer/factory.py
esi_utils_transfer/ftpsender.py
esi_utils_transfer/pdlsender.py
esi_utils_transfer/securesender.py
esi_utils_transfer/sender.py
esi_utils_transfer-0.1.5.dist-info/licenses/LICENSE.md
esi_utils_transfer-0.1.5.dist-info/METADATA
esi_utils_transfer-0.1.5.dist-info/WHEEL
esi_utils_transfer-0.1.5.dist-info/top_level.txt
esi_utils_transfer-0.1.5.dist-info/RECORD
