Metadata-Version: 2.4
Name: esi-utils-transfer
Version: 0.1.5
Summary: USGS Earthquake Impact Utilities for Transferring Data
Author-email: Mike Hearne <mhearne@usgs.gov>
License: License
Keywords: utilities,io
Requires-Python: >=3.8
License-File: LICENSE.md
Requires-Dist: scp>=0.14.0
Requires-Dist: paramiko>=2.10.0
Provides-Extra: build
Requires-Dist: build; extra == "build"
Requires-Dist: twine; extra == "build"
Requires-Dist: check-wheel-contents; extra == "build"
Provides-Extra: dev
Requires-Dist: build>=0.7.0; extra == "dev"
Requires-Dist: black>=21; extra == "dev"
Requires-Dist: flake8>=3.9; extra == "dev"
Requires-Dist: ipython>=7.26; extra == "dev"
Provides-Extra: test
Requires-Dist: pytest>=6.2; extra == "test"
Requires-Dist: pytest-cov>=2.12.0; extra == "test"
Dynamic: license-file
